swing/__init__.py
swing/abc.py
swing/gwo.py
swing/pso.py
swing/version.py
swing/workspace.py
swing_opt-0.1.2.dist-info/LICENSE
swing_opt-0.1.2.dist-info/METADATA
swing_opt-0.1.2.dist-info/WHEEL
swing_opt-0.1.2.dist-info/top_level.txt
swing_opt-0.1.2.dist-info/RECORD
