Metadata-Version: 2.1
Name: swing-opt
Version: 0.1.2
Summary: Swarm intelligence optimization.
Home-page: https://github.com/yqiuu/swing
Author: Yisheng Qiu
License: MIT
License-File: LICENSE
Requires-Dist: numpy (>=1.17)
Requires-Dist: tqdm
